ptlbp/__init__.py
ptlbp/comparisson.py
ptlbp/datasets.py
ptlbp/diff_lbp.py
ptlbp/encoding.py
ptlbp/histograms.py
ptlbp/losses.py
ptlbp/sampling.py
ptlbp/srs.py
ptlbp/testing.py
ptlbp/unpooled_lbp.py
ptlbp/util.py
ptlbp-0.1.0.dist-info/METADATA
ptlbp-0.1.0.dist-info/WHEEL
ptlbp-0.1.0.dist-info/top_level.txt
ptlbp-0.1.0.dist-info/RECORD
